{
    "accounts": [
        {
            "id": "0000000000000005",
            "migrationDate": "2018-08-31T13:44:56Z",
            "email": "dcc18348_296f_483e_b672_8a119396f73c@shutterfly.com"
        },
        {
            "id": "0000000000000008",
            "migrationDate": "2018-09-04T08:44:56Z",
            "email": "abcdda6b_e275_4b0e_baa6_75d626c10e9c@shutterfly.com"
        },
        {
            "id": "0000000000000004",
            "migrationDate": "2018-05-14T18:44:56Z",
            "email": "8255da6b_e275_4b0e_baa6_75d626c10e9c@shutterfly.com"
        },
        {
            "id": "0000000000000001",
            "migrationDate": "2018-04-16T12:44:56Z",
            "email": "8265da6b_e275_4b0e_baa6_75d626c10e9c@shutterfly.com"
        },
        {
            "id": "0000000000000009",
            "migrationDate": "2018-07-07T20:44:56Z",
            "email": "3255da6b_e275_4b0e_baa6_75d626c10e9c@shutterfly.com"
        },
        {
            "id": "0000000000000007",
            "migrationDate": "2018-03-03T04:44:56Z",
            "email": "1155da6b_e275_4b0e_baa6_75d626c10e9c@shutterfly.com"
        },
        {
            "id": "0000000000000003",
            "migrationDate": "2018-01-24T13:44:56Z",
            "email": "1255da6b_e275_4b0e_baa6_75d626c10e9c@shutterfly.com"
        },
        {
            "id": "0000000000000006",
            "migrationDate": "2018-01-24T13:45:56Z",
            "email": "7455da6b_e275_4b0e_baa6_75d626c10e9c@shutterfly.com"
        },
        {
            "id": "0000000000000002",
            "migrationDate": "2018-01-24T13:45:56Z",
            "email": "8255da6b_e275_4b0e_baa6_75d626c10e9c@shutterfly.com"
        }
    ]
}
